ansys/scade/python_wrapper/__init__.py
ansys/scade/python_wrapper/gui.py
ansys/scade/python_wrapper/kcg_data_parser.py
ansys/scade/python_wrapper/kcgpython.py
ansys/scade/python_wrapper/props.py
ansys/scade/python_wrapper/pydata.py
ansys/scade/python_wrapper/python_wrapper.srg
ansys/scade/python_wrapper/python_wrapper23r1.srg
ansys/scade/python_wrapper/python_wrapper24r2.srg
ansys/scade/python_wrapper/reggitext.ps1
ansys/scade/python_wrapper/register.py
ansys/scade/python_wrapper/swan_data_parser.py
ansys/scade/python_wrapper/swanpython.py
ansys/scade/python_wrapper/unregister.py
ansys/scade/python_wrapper/utils.py
ansys/scade/python_wrapper/include/swan_config_default.h
ansys/scade/python_wrapper/lib/Makefile
ansys/scade/python_wrapper/lib/sdyproxy.c
ansys/scade/python_wrapper/lib/sdyproxy.py
ansys/scade/python_wrapper/lib/ssmproxy.py
ansys/scade/python_wrapper/rd/c_gen.py
ansys/scade/python_wrapper/rd/def_gen.py
ansys/scade/python_wrapper/rd/python_gen.py
ansys_scade_python_wrapper-2.2.3.dist-info/entry_points.txt
ansys_scade_python_wrapper-2.2.3.dist-info/LICENSE
ansys_scade_python_wrapper-2.2.3.dist-info/WHEEL
ansys_scade_python_wrapper-2.2.3.dist-info/METADATA
ansys_scade_python_wrapper-2.2.3.dist-info/RECORD
